tectonic/__init__.py
tectonic/ansible.py
tectonic/cli.py
tectonic/client.py
tectonic/client_aws.py
tectonic/client_docker.py
tectonic/client_libvirt.py
tectonic/config.py
tectonic/config_ansible.py
tectonic/config_aws.py
tectonic/config_caldera.py
tectonic/config_docker.py
tectonic/config_elastic.py
tectonic/config_libvirt.py
tectonic/constants.py
tectonic/core.py
tectonic/description.py
tectonic/image_generation/README.md
tectonic/image_generation/bootstrap_win.pkrtpl
tectonic/image_generation/create_image.pkr.hcl
tectonic/image_generation/elastic_agent.yml
tectonic/image_generation/libvirt_conf.yml
tectonic/instance_type.py
tectonic/instance_type_aws.py
tectonic/packer.py
tectonic/packer_aws.py
tectonic/packer_docker.py
tectonic/packer_libvirt.py
tectonic/playbooks/make_request.yml
tectonic/playbooks/services_get_password.yml
tectonic/playbooks/trainees.yml
tectonic/playbooks/wait_for_connection.yml
tectonic/services/ansible/configure_services.yml
tectonic/services/caldera/after_clone.yml
tectonic/services/caldera/agent_install.yml
tectonic/services/caldera/base_config.yml
tectonic/services/caldera/get_info.yml
tectonic/services/caldera/import_resources.yml
tectonic/services/caldera/import_resources_api.yml
tectonic/services/caldera/make_request.yml
tectonic/services/caldera/templates/check-caldera.j2
tectonic/services/caldera/templates/config.j2
tectonic/services/caldera/vars/variables.yml
tectonic/services/elastic/after_clone.yml
tectonic/services/elastic/agent_manage.yml
tectonic/services/elastic/base_config.yml
tectonic/services/elastic/endpoint_install.yml
tectonic/services/elastic/get_info.yml
tectonic/services/elastic/import_resources.yml
tectonic/services/elastic/import_resources_fleet.yml
tectonic/services/elastic/templates/check-fleet.j2
tectonic/services/elastic/templates/check-kibana.j2
tectonic/services/elastic/templates/elasticsearch.j2
tectonic/services/elastic/templates/kibana.j2
tectonic/services/elastic/templates/logstash.j2
tectonic_cyberrange-2.0.1.dist-info/METADATA
tectonic_cyberrange-2.0.1.dist-info/WHEEL
tectonic_cyberrange-2.0.1.dist-info/entry_points.txt
tectonic_cyberrange-2.0.1.dist-info/licenses/LICENSE
tectonic_cyberrange-2.0.1.dist-info/RECORD
