Metadata-Version: 2.4
Name: tectonic-cyberrange
Version: 2.0.1
Summary: A Python package for the Tectonic Cyber Range project.
License: GPL-3.0-or-later
License-File: LICENSE
Keywords: cyberrange,tectonic,ansible,terraform,aws,cloud,security,automation
Author: GSI-Fing-Udelar
Requires-Python: >=3.10,<4.0
Classifier: License :: OSI Approved :: GNU General Public License v3 or later (GPLv3+)
Classifier: Operating System :: OS Independent
Classifier: Programming Language :: Python :: 3
Classifier: Programming Language :: Python :: 3.10
Classifier: Programming Language :: Python :: 3.11
Classifier: Programming Language :: Python :: 3.12
Classifier: Programming Language :: Python :: 3.13
Classifier: Programming Language :: Python :: 3.14
Requires-Dist: ansible (==10.7.0)
Requires-Dist: ansible-runner
Requires-Dist: bcrypt
Requires-Dist: beautifulsoup4
Requires-Dist: boto3
Requires-Dist: botocore
Requires-Dist: bs4
Requires-Dist: certifi
Requires-Dist: cffi
Requires-Dist: charset-normalizer
Requires-Dist: click
Requires-Dist: cryptography (==44.0.3)
Requires-Dist: decorator
Requires-Dist: deprecated
Requires-Dist: docker
Requires-Dist: elasticsearch
Requires-Dist: fabric
Requires-Dist: freezegun
Requires-Dist: idna
Requires-Dist: invoke
Requires-Dist: jmespath
Requires-Dist: libvirt-python
Requires-Dist: packaging
Requires-Dist: packer.py
Requires-Dist: paramiko
Requires-Dist: passlib
Requires-Dist: prettytable
Requires-Dist: pycparser
Requires-Dist: pynacl
Requires-Dist: pyopenssl (>=24.3)
Requires-Dist: python-dateutil
Requires-Dist: python-terraform
Requires-Dist: pyyaml
Requires-Dist: requests (==2.32.5)
Requires-Dist: requests-toolbelt
Requires-Dist: s3transfer
Requires-Dist: six
Requires-Dist: urllib3
Requires-Dist: wrapt
Project-URL: Bug Tracker, https://github.com/GSI-Fing-Udelar/tectonic/issues
Project-URL: Documentation, https://github.com/GSI-Fing-Udelar/tectonic/tree/main/docs
Project-URL: Homepage, https://www.fing.edu.uy/inco/proyectos/tectonic
Project-URL: Repository, https://github.com/GSI-Fing-Udelar/tectonic.git
